simli/__init__.py
simli/daily_renderer.py
simli/livekit_renderer.py
simli/renderers.py
simli/simli.py
simli/utils.py
simli_ai-1.0.3.dist-info/licenses/LICENSE
simli_ai-1.0.3.dist-info/METADATA
simli_ai-1.0.3.dist-info/WHEEL
simli_ai-1.0.3.dist-info/top_level.txt
simli_ai-1.0.3.dist-info/RECORD
