Metadata-Version: 2.4
Name: simli-ai
Version: 1.0.3
Summary: Add your description here
License: MIT License
Project-URL: Homepage, https://github.com/simliai/simli-client-py
Project-URL: Bug Reports, https://github.com/simliai/simli-client-py/issues
Project-URL: Source, https://github.com/simliai/simli-client-py
License-File: LICENSE
Requires-Dist: aiortc
Requires-Dist: websockets
Requires-Dist: httpx
Requires-Dist: numpy
Requires-Dist: av>=13
Requires-Dist: livekit>=1.0.1
Provides-Extra: local
Requires-Dist: opencv-python; extra == "local"
Requires-Dist: pyaudio; extra == "local"
Provides-Extra: daily
Requires-Dist: daily-python>=0.13.0; extra == "daily"
Provides-Extra: livekit
Requires-Dist: livekit-api>=0.8.0; extra == "livekit"
Requires-Dist: livekit>=0.18.1; extra == "livekit"
Dynamic: license-file
